easy_net_tf/__init__.py
easy_net_tf/nn/__init__.py
easy_net_tf/nn/cnn.py
easy_net_tf/nn/fully_connect_net.py
easy_net_tf/nn/mobile_net_v2.py
easy_net_tf/utility/__init__.py
easy_net_tf/utility/accuracy.py
easy_net_tf/utility/anchor.py
easy_net_tf/utility/bounding.py
easy_net_tf/utility/file.py
easy_net_tf/utility/image.py
easy_net_tf/utility/landmark.py
easy_net_tf/utility/loss.py
easy_net_tf/utility/slide_window.py
easy_net_tf/utility/variable.py
easy_net_tf-0.0.30.dist-info/METADATA
easy_net_tf-0.0.30.dist-info/RECORD
easy_net_tf-0.0.30.dist-info/WHEEL
easy_net_tf-0.0.30.dist-info/top_level.txt
network_utility/__init__.py
network_utility/fully_connected_layer.py
network_utility/mobilenet_v2.py
network_utility/shuffle_net.py
network_utility/utility_network.py
