Metadata-Version: 2.1
Name: easy-net-tf
Version: 0.0.30
Summary: A tensorflow-based network utility lib.
Home-page: https://gitlab.espressif.cn:6688/yhy/Network
Author: Ye Hang'yang
Author-email: yehangyang@qq.com
License: MIT
Platform: UNKNOWN
Classifier: Programming Language :: Python :: 3
Classifier: License :: OSI Approved :: MIT License
Classifier: Operating System :: MacOS
Classifier: Operating System :: Microsoft
Classifier: Operating System :: Unix
Classifier: Topic :: Software Development :: Libraries :: Python Modules
